oliker_prussner_method/__init__.py
oliker_prussner_method/core.py
oliker_prussner_method/initialisation.py
oliker_prussner_method/plotting.py
oliker_prussner_method/triangulation.py
oliker_prussner_method-1.0.1.dist-info/licenses/LICENSE
oliker_prussner_method-1.0.1.dist-info/METADATA
oliker_prussner_method-1.0.1.dist-info/WHEEL
oliker_prussner_method-1.0.1.dist-info/top_level.txt
oliker_prussner_method-1.0.1.dist-info/RECORD
