Metadata-Version: 2.4
Name: oliker_prussner_method
Version: 1.0.1
Summary: A python implementation of the Oliker-Prussner-Method for solving the 2 dimensional Monge-Ampère-Equation.
Author: Yannick Höffner
License-Expression: MIT
Project-URL: Homepage, https://github.com/yannick-hoeffner/oliker_prussner_method
Project-URL: Issues, https://github.com/yannick-hoeffner/oliker_prussner_method/issues
Keywords: monge-ampere,monge-ampere-equation,oliker-prussner-method,numerical-methods,numerical-analysis,partial-differential-equations,pde,2d-pde,2d-monge-ampere-equation
Classifier: Development Status :: 5 - Production/Stable
Classifier: Intended Audience :: Science/Research
Classifier: Intended Audience :: Developers
Classifier: Programming Language :: Python :: 3
Classifier: Programming Language :: Python :: 3.12
Classifier: Programming Language :: Python :: 3.13
Classifier: Programming Language :: Python :: 3 :: Only
Classifier: Topic :: Scientific/Engineering
Classifier: Topic :: Scientific/Engineering :: Mathematics
Classifier: Topic :: Scientific/Engineering :: Physics
Classifier: Typing :: Typed
Classifier: Operating System :: OS Independent
Requires-Python: >=3.12
License-File: LICENSE
Requires-Dist: numpy>=2.1.3
Requires-Dist: numba>=0.61.0
Requires-Dist: scipy>=1.15.2
Requires-Dist: matplotlib>=3.10.1
Dynamic: license-file
